README.rst
setup.py
striptls/__init__.py
striptls/__main__.py
striptls/striptls.py
striptls.egg-info/PKG-INFO
striptls.egg-info/SOURCES.txt
striptls.egg-info/dependency_links.txt
striptls.egg-info/top_level.txt